README.rst
setup.py
linemode/__init__.py
linemode/base.py
linemode/exceptions.py
linemode/spooler.py
linemode.egg-info/PKG-INFO
linemode.egg-info/SOURCES.txt
linemode.egg-info/dependency_links.txt
linemode.egg-info/not-zip-safe
linemode.egg-info/requires.txt
linemode.egg-info/top_level.txt
linemode/drivers/__init__.py
linemode/drivers/command_list.py
linemode/drivers/star.py
linemode/renderers/__init__.py
linemode/renderers/command_list.py
linemode/renderers/xml.py
linemode/tests/__init__.py
linemode/tests/test_command_list_printer.py
linemode/tests/test_command_list_renderer.py
linemode/tests/test_loader.py
linemode/tests/test_spooler.py
linemode/tests/test_star.py
linemode/tests/test_xml_renderer.py