Metadata-Version: 1.1
Name: linemode
Version: 0.4.0
Summary: Drivers and templates for thermal printers
Home-page: github.com/bwhmather/python-linemode
Author: Ben Mather
Author-email: bwhmather@bwhmather.com
License: BSD
Platform: UNKNOWN
Classifier: Development Status :: 4 - Beta
Classifier: Intended Audience :: Developers
Classifier: License :: OSI Approved :: BSD License
Classifier: Operating System :: OS Independent
Classifier: Programming Language :: Python :: 3
Classifier: Topic :: Software Development :: Libraries :: Python Modules
Classifier: Topic :: System :: Hardware :: Hardware Drivers
Classifier: Topic :: Printing
